gameball/__init__.py
gameball/api_requestor.py
gameball/constants.py
gameball/gameball_response.py
gameball/http_client.py
gameball/utils.py
gameball/version.py
gameball/api_resources/__init__.py
gameball/api_resources/action.py
gameball/api_resources/coupon.py
gameball/api_resources/events.py
gameball/api_resources/player.py
gameball/api_resources/referral.py
gameball/api_resources/transactions.py
gameball/exceptions/__init__.py
gameball/exceptions/gameball_exception.py
gameball/models/__init__.py
gameball/models/action_object.py
gameball/models/coupon_object.py
gameball/models/event_object.py
gameball/models/player_object.py
gameball/models/referral_object.py
gameball/models/reward_object.py
gameball-1.0.0.dist-info/LICENSE
gameball-1.0.0.dist-info/METADATA
gameball-1.0.0.dist-info/WHEEL
gameball-1.0.0.dist-info/top_level.txt
gameball-1.0.0.dist-info/RECORD
