Metadata-Version: 2.1
Name: gameball
Version: 1.0.0
Summary: Gameball Python SDK provides convinient access to the Gameball API frpm applicatopns written in the Python langauage
Home-page: https://github.com/gameballers/gameball-python
Author: Gameball
Author-email: support@gameball.co
License: UNKNOWN
Platform: UNKNOWN
Requires-Python: >=3.4
